<?xml version="1.0" encoding="utf-8"?>
<annotation>
   <folder>CNNData</folder>
   <filename>17223.jpg</filename>
   <source>
      <database/>
      <annotation/>
      <image/>
      <flickerid/>
   </source>
   <owner>
      <flickerid/>
      <name>Saadia K. Gabriel</name>
   </owner>
   <size>
      <width>600</width>
      <height>600</height>
      <depth>3</depth>
   </size>
   <segmented>0</segmented>
   <object>
      <name>roost</name>
      <pose>Unspecified</pose>
      <truncated>0</truncated>
      <difficult>0</difficult>
      <bndbox>
         <xmin>193</xmin>
         <ymin>312</ymin>
         <xmax>217</xmax>
         <ymax>336</ymax>
      </bndbox>
   </object>
   <object>
      <name>roost</name>
      <pose>Unspecified</pose>
      <truncated>0</truncated>
      <difficult>0</difficult>
      <bndbox>
         <xmin>196</xmin>
         <ymin>205</ymin>
         <xmax>220</xmax>
         <ymax>229</ymax>
      </bndbox>
   </object>
   <object>
      <name>roost</name>
      <pose>Unspecified</pose>
      <truncated>0</truncated>
      <difficult>0</difficult>
      <bndbox>
         <xmin>264</xmin>
         <ymin>218</ymin>
         <xmax>294</xmax>
         <ymax>248</ymax>
      </bndbox>
   </object>
   <object>
      <name>roost</name>
      <pose>Unspecified</pose>
      <truncated>0</truncated>
      <difficult>0</difficult>
      <bndbox>
         <xmin>303</xmin>
         <ymin>265</ymin>
         <xmax>324</xmax>
         <ymax>286</ymax>
      </bndbox>
   </object>
</annotation>